[{
  "name": "Tenerife",
  "maps": {
    "Sever ostrova": "https://mapy.cz/s/cusobomoco",
    "Los Gigantes": "https://mapy.cz/s/pumuvumome",
    "Santa Cruz": "https://mapy.cz/s/momozojofa"
  },
  "places": "https://goo.gl/maps/bQp4nh7SffCdoPdp9",
  "trips": [
    {
      "id": "0",
      "location": "Los Gigantes",
      "image": "images/tenerife/chinyero-volcano.png",
      "header": "Výstup na vulkán Chinyero",
      "hikeTimeRange": "4:15",
      "carTimeRange": "TBA",
      "hikeLength": "13,4km",
      "ascent": "382m",
      "descent": "382m",
      "info": "https://docs.google.com/document/d/1uCXWVlWXiCgo3Mk-BgJScw72nxUH8rRmNU8t0PLoCSY/edit?usp=sharing",
      "url": "https://mapy.cz/s/forolumelu",
      "parking": "https://goo.gl/maps/mcKcGtJB2qDrRfyJ7"
    },
    {
      "id": "1",
      "location": "Los Gigantes",
      "image": "images/tenerife/montanas-negras.jpeg",
      "header": "Okruh černými horami",
      "hikeTimeRange": "4:00",
      "carTimeRange": "TBA",
      "hikeLength": "12,1km",
      "ascent": "399m",
      "info": "https://docs.google.com/document/d/1_ZNv0onx-6giUb0NKzBE5ssI8hwp_hsZd1jVj4EPUrk/edit?usp=sharing",
      "url": "https://mapy.cz/s/bobugesuse",
      "parking": "https://goo.gl/maps/HN64qNHWgQB16esSA"
    },
    {
      "id": "2",
      "location": "Los Gigantes",
      "image": "images/tenerife/roques-de-garcia.jpeg",
      "header": "Skalní útvary Roques del García",
      "hikeTimeRange": "1:30",
      "carTimeRange": "TBA",
      "hikeLength": "3,3km",
      "ascent": "129m",
      "info": "https://docs.google.com/document/d/1gKytAliSgkA2me-cJZ2JBVWBgRqVI8UldawEbhCvD3k/edit?usp=sharing",
      "url": "https://mapy.cz/s/fugaluvuju",
      "parking": "https://goo.gl/maps/6YZDtVBEJkGg93Pn8"
    },
    {
      "id": "3",
      "location": "Sever ostrova",
      "image": "images/tenerife/roque-de-taborno.jpg",
      "header": "Okruh Roque de Taborno",
      "hikeTimeRange": "1:30",
      "carTimeRange": "0:26",
      "hikeLength": "4km",
      "ascent": "129m",
      "info": "https://docs.google.com/document/d/1zWbLPCbXlEPFPuMM0qwlspAyY3_IF5qfQNvElfE2vGo/edit?usp=sharing",
      "url": "https://mapy.cz/s/pokecaloma",
      "parking": "https://goo.gl/maps/eLh9em1wRxkD9X1XA"
    },
    {
      "id": "4",
      "location": "Los Gigantes",
      "image": "images/tenerife/pico-del-teide.jpg",
      "header": "Pod vrchol Pico del Teide",
      "hikeTimeRange": "7:37",
      "carTimeRange": "1:00",
      "hikeLength": "18,8km",
      "ascent": "1387m",
      "info": "",
      "url": "https://mapy.cz/s/bevapulese",
      "parking": "https://goo.gl/maps/KzJvDtRx7R23RmBw9"
    },
    {
      "id": "5",
      "location": "Sever ostrova",
      "image": "images/tenerife/sendero-de-los-sentidos.jpg",
      "header": "Okruh Sendero de los Sentidos",
      "hikeTimeRange": "0:37",
      "carTimeRange": "0:26",
      "hikeLength": "1,3km",
      "ascent": "136m",
      "info": "https://docs.google.com/document/d/1z9SCzR8BZneENbIWik1iYhO1P8Np0FUiDg9lB5Sc-R0/edit?usp=sharing",
      "url": "https://mapy.cz/s/dotomucebu",
      "parking": "https://goo.gl/maps/VXL1zSm1ZSubaCQT6"
    },
    {
      "id": "6",
      "location": "Sever ostrova",
      "image": "images/tenerife/anaga.jpeg",
      "header": "Okruh pohořím Anaga",
      "hikeTimeRange": "7:00",
      "carTimeRange": "1:00",
      "hikeLength": "14.2km",
      "ascent": "1432m",
      "info": "https://docs.google.com/document/d/1x7TEtcfA_bHK0fyEcGlYaUAL8pqfJY7JLzITZ8ekusk/edit?usp=sharing",
      "url": "https://mapy.cz/s/falomokeme",
      "parking": "https://goo.gl/maps/s6ZUFQC3nm4w9gae6"
    },
    {
      "id": "7",
      "location": "Sever ostrova",
      "image": "images/tenerife/anaga.jpeg",
      "header": "Okruh pohořím Anaga - kratší",
      "hikeTimeRange": "3:45",
      "carTimeRange": "1:00",
      "hikeLength": "7km",
      "ascent": "847m",
      "info": "https://docs.google.com/document/d/1x7TEtcfA_bHK0fyEcGlYaUAL8pqfJY7JLzITZ8ekusk/edit?usp=sharing",
      "url": "https://mapy.cz/s/jubahojuho",
      "parking": "https://goo.gl/maps/s6ZUFQC3nm4w9gae6"
    },
    {
      "id": "8",
      "location": "Los Gigantes",
      "image": "images/tenerife/paisaje-lunar.jpeg",
      "header": "Okruh měsíční krajinou Paisaje Lunar",
      "hikeTimeRange": "2:55",
      "carTimeRange": "1:09",
      "hikeLength": "8,2km",
      "ascent": "298m",
      "info": "https://docs.google.com/document/d/15of5GweF1JGXVXKIIox1_8kLi6eO5hOCh58TfvxWhpo/edit?usp=sharing",
      "url": "https://mapy.cz/s/pavodudamu",
      "parking": "https://goo.gl/maps/EbLCcbnuF4iq6mBz9"
    },
    {
      "id": "9",
      "location": "Los Gigantes",
      "image": "images/tenerife/montana-negra.jpg",
      "header": "Okruh kolem sopky Montaña Negra",
      "hikeTimeRange": "1:32",
      "carTimeRange": "0:43",
      "hikeLength": "4,5km",
      "ascent": "142m",
      "info": "https://docs.google.com/document/d/1LSPn-SLbDtcGnDNeYCHI5fGW5FGg_x4gvGjuBSRrjx8/edit?usp=sharing",
      "url": "https://mapy.cz/s/fohopazatu",
      "parking": "https://goo.gl/maps/EsQzcLs5hPN5EgT98"
    },
    {
      "id": "10",
      "location": "Los Gigantes",
      "image": "images/tenerife/garachico.jpeg",
      "header": "Městečko Garachico",
      "hikeTimeRange": "0:26",
      "carTimeRange": "0:56",
      "hikeLength": "1,2km",
      "ascent": "42m",
      "info": "https://docs.google.com/document/d/1DO-u6Z5fH0RCKTenCPyE8xRdyhGhdHbSoTC0UTNn4qg/edit?usp=sharing",
      "url": "https://mapy.cz/s/gugulalaga",
      "parking": "https://goo.gl/maps/gL2YBhG3EHThp8zK8"
    },
    {
      "id": "10",
      "location": "Sever ostrova",
      "image": "images/tenerife/rybi-stezka.jpeg",
      "header": "Rybí stezka Puerto de la Cruz",
      "hikeTimeRange": "0:21",
      "carTimeRange": "0:20",
      "hikeLength": "1,2km",
      "ascent": "11m",
      "info": "https://docs.google.com/document/d/1PZTCfNN9BGGcget9oe5BfCk3Z-KTuj7jaJ0AriR-pck/edit?usp=sharing",
      "url": "https://mapy.cz/s/forudatoku",
      "parking": "https://goo.gl/maps/Xwctiq76A1su7ber9"
    }
  ]
  },
  {
   "name": "Beskydy",
   "trips": [
        {
          "id": "0",
          "location": "Beskydy",
          "image": "images/tenerife/barranca-masca.jpeg",
          "header": "Výšlap k lanovce",
          "hikeTimeRange": "8h",
          "ascent": "800m",
          "descent": "500m",
          "url": "https://www.mapy.cz"
        },
        {
          "id": "1",
          "location": "Beskydy",
          "image": "images/tenerife/barranca-masca.jpeg",
          "header": "Výšlap k jezeru",
          "hikeTimeRange": "5,5h",
          "ascent": "800m",
          "descent": "500m",
          "url": "https://www.mapy.cz"
        }
      ]
  }
]
